summarease/__init__.py
summarease/summarize.py
summarease/summarize_dtypes.py
summarease/summarize_numeric.py
summarease/summarize_target.py
summarease-1.1.4.dist-info/LICENSE
summarease-1.1.4.dist-info/METADATA
summarease-1.1.4.dist-info/WHEEL
summarease-1.1.4.dist-info/RECORD
