Metadata-Version: 2.3
Name: summarease
Version: 1.1.4
Summary: A package that provides quick summaries of datasets, including data types, missing value counts, and basic statistics.
License: MIT
Author: Hrayr Muradyan, Yun Zhou, Stephanie Wu, Zuer Zhong
Requires-Python: >=3.11,<4.0
Classifier: License :: OSI Approved :: MIT License
Classifier: Programming Language :: Python :: 3
Classifier: Programming Language :: Python :: 3.11
Classifier: Programming Language :: Python :: 3.12
Classifier: Programming Language :: Python :: 3.13
Requires-Dist: altair (>=5.5.0,<6.0.0)
Requires-Dist: fpdf (>=1.7.2,<2.0.0)
Requires-Dist: numpy (>=2.2.2,<3.0.0)
Requires-Dist: pandas (>=2.2.3,<3.0.0)
Requires-Dist: pillow (>=11.1.0,<12.0.0)
Requires-Dist: pytest (>=8.3.4,<9.0.0)
Requires-Dist: pytest-cov (>=6.0.0,<7.0.0)
Requires-Dist: scikit-learn (>=1.6.1,<2.0.0)
Requires-Dist: sphinx-material (>=0.0.36,<0.0.37)
Requires-Dist: vl-convert-python (>=1.7.0,<2.0.0)
